sutools/__init__.py
sutools/bench_handler.py
sutools/cli_handler.py
sutools/log_handler.py
sutools/meta_handler.py
sutools-0.2.4.dist-info/LICENSE
sutools-0.2.4.dist-info/METADATA
sutools-0.2.4.dist-info/WHEEL
sutools-0.2.4.dist-info/top_level.txt
sutools-0.2.4.dist-info/RECORD
