Metadata-Version: 2.1
Name: sutools
Version: 0.2.4
Summary: su (Super User) tools; per module utilities, designed to be lightweight, easy to configure, and reduce boilerplate code.
Home-page: https://github.com/aastopher/sutools
Author: Aaron Stopher
Project-URL: Documentation, https://sutools.readthedocs.io
Project-URL: Bug Tracker, https://github.com/aastopher/sutools/issues
Keywords: logs,logger,logging,cli,utils,performance counter,benchmark
Classifier: Programming Language :: Python :: 3
Classifier: License :: OSI Approved :: MIT License
Classifier: Operating System :: OS Independent
Requires-Python: >=3.6
License-File: LICENSE
